ahasura.py
ahasura-1.4.2.dist-info/LICENSE
ahasura-1.4.2.dist-info/WHEEL
ahasura-1.4.2.dist-info/METADATA
ahasura-1.4.2.dist-info/RECORD
