Metadata-Version: 2.1
Name: ahasura
Version: 1.4.2
Summary: Async and sync Hasura client
Home-page: https://github.com/cmr-surgical/ahasura
License: MIT
Keywords: async,sync,ahasura,hasura,client
Author: Denis Ryzhkov
Author-email: denis.ryzhkov@cmrsurgical.com
Requires-Python: >=3.8,<4.0
Classifier: License :: OSI Approved :: MIT License
Classifier: Programming Language :: Python :: 3
Classifier: Programming Language :: Python :: 3.10
Classifier: Programming Language :: Python :: 3.8
Classifier: Programming Language :: Python :: 3.9
Requires-Dist: httpx (>=0,<1)
Project-URL: Hasura, https://hasura.io/
Project-URL: Hasura docs, https://hasura.io/docs/latest/graphql/core/index.html
Project-URL: Repository, https://github.com/cmr-surgical/ahasura
